markdown_translate_ai/__init__.py
markdown_translate_ai/translator.py
markdown_translate_ai/config/__init__.py
markdown_translate_ai/config/models_config.py
markdown_translate_ai/config/prompts.py
markdown_translate_ai/providers/__init__.py
markdown_translate_ai/providers/anthropic.py
markdown_translate_ai/providers/base.py
markdown_translate_ai/providers/deepseek.py
markdown_translate_ai/providers/gemini.py
markdown_translate_ai/providers/openai.py
markdown_translate_ai/util/__init__.py
markdown_translate_ai/util/statistics.py
markdown_translate_ai/util/validator.py
markdown_translate_ai-0.1.3.dist-info/LICENSE
markdown_translate_ai-0.1.3.dist-info/METADATA
markdown_translate_ai-0.1.3.dist-info/WHEEL
markdown_translate_ai-0.1.3.dist-info/entry_points.txt
markdown_translate_ai-0.1.3.dist-info/top_level.txt
markdown_translate_ai-0.1.3.dist-info/RECORD
