Metadata-Version: 2.2
Name: markdown-translate-ai
Version: 0.1.3
Summary: Python package to translate markdown files with multiple AI service providers.
Home-page: https://github.com/KevinRohn/markdown-translate-ai
Author: Kevin Rohn
Author-email: kevin@rohn.tech
License: MIT
Project-URL: Source Code, https://github.com/KevinRohn/markdown-translate-ai
Classifier: Programming Language :: Python :: 3.12
Classifier: Development Status :: 3 - Alpha
Classifier: Environment :: Console
Classifier: Intended Audience :: Developers
Classifier: License :: OSI Approved :: MIT License
Requires-Python: >=3.12
License-File: LICENSE
Requires-Dist: openai
Requires-Dist: httpx
Requires-Dist: marko
Requires-Dist: httpx[http2]
Dynamic: author
Dynamic: author-email
Dynamic: classifier
Dynamic: description
Dynamic: description-content-type
Dynamic: home-page
Dynamic: license
Dynamic: project-url
Dynamic: requires-dist
Dynamic: requires-python
Dynamic: summary
